dictionary/__init__.py
dictionary/dictionary.py
hw1_dictionary-2.0.1.dist-info/METADATA
hw1_dictionary-2.0.1.dist-info/WHEEL
hw1_dictionary-2.0.1.dist-info/top_level.txt
hw1_dictionary-2.0.1.dist-info/RECORD
