Metadata-Version: 2.1
Name: hw1-dictionary
Version: 2.0.1
Summary: UNKNOWN
Author: Funda Tan
License: UNKNOWN
Platform: UNKNOWN
Requires-Python: >=3.8
Requires-Dist: requests (>=2.23.0)
